recursivenamespace/__init__.py
recursivenamespace/main.py
RecursiveNamespace-0.2.2.dist-info/LICENSE
RecursiveNamespace-0.2.2.dist-info/METADATA
RecursiveNamespace-0.2.2.dist-info/WHEEL
RecursiveNamespace-0.2.2.dist-info/top_level.txt
RecursiveNamespace-0.2.2.dist-info/RECORD
