Metadata-Version: 2.1
Name: RecursiveNamespace
Version: 0.2.2
Summary: Recursive Namespace. An extension of SimpleNamespace
Home-page: https://github.com/HessamLa/RecursiveNamespace
Author: Hamidreza Lotfalizadeh (Hessam)
Author-email: HLOTFALI_at_PURDUE_EDU@random.site
Classifier: Programming Language :: Python :: 3
Classifier: License :: OSI Approved :: MIT License
Classifier: Operating System :: OS Independent
Requires-Python: >=3.6
License-File: LICENSE
